<?xml version="1.0" encoding="UTF-8" standalone="yes"?>
<features xmlns="http://karaf.apache.org/xmlns/features/v1.2.0" name="HyperIoTHBaseConnector-features">
  <feature name="hyperiot-hbaseconnector" version="2.3.0" description="All  HyperIoT HyperIoTHBaseConnector modules">
    <feature>hyperiot-base</feature>
    <feature>hyperiot-hbaseconnector-basic</feature>
    <bundle>mvn:it.acsoftware.hyperiot.hbase.connector/HyperIoTHBaseConnector-service-rest/2.3.0</bundle>
  </feature>
  <feature name="hyperiot-hbaseconnector-basic" version="2.3.0" description="All  HyperIoT HyperIoTHBaseConnector modules with NO rest services">
    <feature>hyperiot-base-basic</feature>
    <bundle>mvn:it.acsoftware.hyperiot.hbase.connector/HyperIoTHBaseConnector-util/2.3.0</bundle>
    <bundle>mvn:it.acsoftware.hyperiot.hbase.connector/HyperIoTHBaseConnector-actions/2.3.0</bundle>
    <bundle>mvn:it.acsoftware.hyperiot.hbase.connector/HyperIoTHBaseConnector-api/2.3.0</bundle>
    <bundle>mvn:it.acsoftware.hyperiot.hbase.connector/HyperIoTHBaseConnector-model/2.3.0</bundle>
    <bundle>mvn:it.acsoftware.hyperiot.hbase.connector/HyperIoTHBaseConnector-service/2.3.0</bundle>
  </feature>
</features>